cjunct/__init__.py
cjunct/actions/__init__.py
cjunct/actions/base.py
cjunct/actions/bundled/__init__.py
cjunct/actions/bundled/docker_shell.py
cjunct/actions/bundled/echo.py
cjunct/actions/bundled/shell.py
cjunct/actions/constants.py
cjunct/actions/types.py
cjunct/config/__init__.py
cjunct/config/constants/__init__.py
cjunct/config/constants/cli.py
cjunct/config/constants/helpers.py
cjunct/config/environment.py
cjunct/console.py
cjunct/display/__init__.py
cjunct/display/base.py
cjunct/display/color.py
cjunct/display/default.py
cjunct/exceptions.py
cjunct/loader/__init__.py
cjunct/loader/base.py
cjunct/loader/default.py
cjunct/loader/helpers.py
cjunct/py.typed
cjunct/rendering/__init__.py
cjunct/rendering/constants.py
cjunct/rendering/containers.py
cjunct/rendering/tokenizing.py
cjunct/runner.py
cjunct/strategy.py
cjunct/tools/inspect.py
cjunct/tools/proxy.py
cjunct/types.py
cjunct/version.py
cjunct/workflow.py
cjunct-2.2.2.dist-info/LICENSE
cjunct-2.2.2.dist-info/METADATA
cjunct-2.2.2.dist-info/WHEEL
cjunct-2.2.2.dist-info/entry_points.txt
cjunct-2.2.2.dist-info/RECORD
