Metadata-Version: 2.1
Name: cjunct
Version: 2.2.2
Summary: Declarative task runner
Home-page: https://github.com/reartnew/cjunct
License: MIT
Author: Artem Novikov
Author-email: artnew@list.ru
Requires-Python: >=3.8.1,<3.13
Classifier: Development Status :: 4 - Beta
Classifier: License :: OSI Approved :: MIT License
Classifier: Programming Language :: Python :: 3
Classifier: Programming Language :: Python :: 3.9
Classifier: Programming Language :: Python :: 3.10
Classifier: Programming Language :: Python :: 3.11
Classifier: Programming Language :: Python :: 3.12
Classifier: Programming Language :: Python :: 3.8
Classifier: Typing :: Typed
Provides-Extra: docker
Requires-Dist: aiodocker (>=0.21.0,<0.22.0) ; extra == "docker"
Requires-Dist: async-shell (>=1.0.7,<2.0.0)
Requires-Dist: classlogging (>=1.1.1,<2.0.0)
Requires-Dist: click (>=8.1.7,<9.0.0)
Requires-Dist: dacite (>=1.8.1,<2.0.0)
Requires-Dist: inquirer (>=3.2.3,<4.0.0)
Requires-Dist: lazy-object-proxy (>=1.10.0,<2.0.0)
Requires-Dist: named-env (>=2.3.2,<3.0.0)
Requires-Dist: python-dotenv (>=1.0.1,<2.0.0)
Requires-Dist: pyyaml (>=6.0.1,<7.0.0)
Project-URL: Repository, https://github.com/reartnew/cjunct
